bazis/contrib/permit/__init__.py
bazis/contrib/permit/_version.py
bazis/contrib/permit/admin.py
bazis/contrib/permit/admin_abstract.py
bazis/contrib/permit/apps.py
bazis/contrib/permit/conf.py
bazis/contrib/permit/models.py
bazis/contrib/permit/models_abstract.py
bazis/contrib/permit/router.py
bazis/contrib/permit/routes.py
bazis/contrib/permit/routes_abstract.py
bazis/contrib/permit/schemas.py
bazis/contrib/permit/services.py
bazis/contrib/permit/signals.py
bazis/contrib/permit/utils.py
bazis/contrib/permit/locale/messages.pot
bazis/contrib/permit/locale/en/LC_MESSAGES/django.mo
bazis/contrib/permit/locale/en/LC_MESSAGES/django.po
bazis/contrib/permit/locale/ru/LC_MESSAGES/django.mo
bazis/contrib/permit/locale/ru/LC_MESSAGES/django.po
bazis/contrib/permit/migrations/0001_initial.py
bazis/contrib/permit/migrations/0002_alter_grouppermission_permissions.py
bazis/contrib/permit/migrations/0003_alter_grouppermission_slug_alter_permission_slug_and_more.py
bazis/contrib/permit/migrations/0004_alter_grouppermission_slug_alter_permission_slug_and_more.py
bazis/contrib/permit/migrations/0005_alter_grouppermission_slug_alter_permission_slug_and_more.py
bazis/contrib/permit/migrations/0006_remove_grouppermission_name_remove_role_name_and_more.py
bazis/contrib/permit/migrations/__init__.py
bazis_permit-2.2.0.dist-info/METADATA
bazis_permit-2.2.0.dist-info/WHEEL
bazis_permit-2.2.0.dist-info/top_level.txt
bazis_permit-2.2.0.dist-info/RECORD
